TbDataCollection/__init__.py
TbDataCollection/_login.py
TbDataCollection/_utils.py
TbDataCollection/branding/_dict.py
TbDataCollection/branding/branding.py
TbDataCollection/branding/report.py
TbDataCollection/collector.py
TbDataCollection/myseller/_dict.py
TbDataCollection/myseller/_utils.py
TbDataCollection/myseller/myseller.py
TbDataCollection/myseller/one.py
TbDataCollection/sycm/_dict.py
TbDataCollection/sycm/_utils.py
TbDataCollection/sycm/goods.py
TbDataCollection/sycm/home.py
TbDataCollection/sycm/self_analysis.py
TbDataCollection/sycm/service.py
TbDataCollection/sycm/sycm.py
tb_data_collection-1.0.17.dist-info/LICENSE
tb_data_collection-1.0.17.dist-info/METADATA
tb_data_collection-1.0.17.dist-info/WHEEL
tb_data_collection-1.0.17.dist-info/RECORD
